Metadata-Version: 2.1
Name: odoo13-addon-l10n-us-form-1099
Version: 13.0.1.0.1
Summary: Manage 1099 Types and Suppliers
Home-page: https://github.com/OCA/l10n-usa
Author: Open Source Integrators, Brian McMaster, Odoo Community Association (OCA)
Author-email: support@odoo-community.org
License: AGPL-3
Platform: UNKNOWN
Classifier: Programming Language :: Python
Classifier: Framework :: Odoo
Classifier: License :: OSI Approved :: GNU Affero General Public License v3
Classifier: Development Status :: 5 - Production/Stable
Requires-Python: >=3.5
Requires-Dist: odoo (<13.1dev,>=13.0a)
